cuteSymbols/__init__.py
cuteSymbols/cuteSymbols.py
cute_symbols-1.0.1.dist-info/licenses/LICENSE
tests/__init__.py
tests/tests.py
cute_symbols-1.0.1.dist-info/METADATA
cute_symbols-1.0.1.dist-info/WHEEL
cute_symbols-1.0.1.dist-info/top_level.txt
cute_symbols-1.0.1.dist-info/RECORD
