Metadata-Version: 2.4
Name: cute-symbols
Version: 1.0.1
Summary: A Python library for managing and accessing cute emoji symbols 🔥
Home-page: https://github.com/LucioPG/cutesymbols
Author: Lucio Di Capua
Author-email: lucio.di.capua@gmail.com
License: MIT
Project-URL: Bug Tracker, https://github.com/LucioPG/cutesymbols/issues
Project-URL: Documentation, https://github.com/LucioPG/cutesymbols/wiki
Project-URL: Source Code, https://github.com/LucioPG/cutesymbols
Keywords: emoji symbols unicode cute icons console logging cli terminal
Platform: any
Classifier: Development Status :: 5 - Production/Stable
Classifier: Intended Audience :: Developers
Classifier: License :: OSI Approved :: MIT License
Classifier: Operating System :: OS Independent
Classifier: Programming Language :: Python :: 3
Classifier: Programming Language :: Python :: 3.8
Classifier: Programming Language :: Python :: 3.9
Classifier: Programming Language :: Python :: 3.10
Classifier: Programming Language :: Python :: 3.11
Classifier: Programming Language :: Python :: 3.12
Classifier: Topic :: Software Development :: Libraries :: Python Modules
Classifier: Topic :: Utilities
Classifier: Topic :: Text Processing
Classifier: Topic :: Multimedia :: Graphics :: Presentation
Requires-Python: >=3.8
License-File: LICENSE
Dynamic: author
Dynamic: author-email
Dynamic: classifier
Dynamic: description
Dynamic: description-content-type
Dynamic: home-page
Dynamic: keywords
Dynamic: license
Dynamic: license-file
Dynamic: platform
Dynamic: project-url
Dynamic: requires-python
Dynamic: summary
